setup.py
google_parser/__init__.py
google_parser/debug.py
google_parser/exceptions.py
google_parser/google.py
google_parser.egg-info/PKG-INFO
google_parser.egg-info/SOURCES.txt
google_parser.egg-info/dependency_links.txt
google_parser.egg-info/requires.txt
google_parser.egg-info/top_level.txt
google_query/__init__.py