Metadata-Version: 1.1
Name: google-parser
Version: 0.0.146
Summary: Convert html to snippets
Home-page: https://github.com/KokocGroup/google-parser
Author: UNKNOWN
Author-email: UNKNOWN
License: UNKNOWN
Download-URL: https://github.com/KokocGroup/google-parser/tarball/v0.0.146
Platform: UNKNOWN
